{"name":"Eventspace.js","tagline":"An event organizer for javascript","body":"#What is it\r\nEventspace.js is a library to manage events in spaces.\r\nYou can have different spaces during life course of your web application and with Eventspace.js you can set different handler for same nodes in every space and manage those different phases.\r\n\r\n###What is a Space\r\nA space is a phase of your web page (or web application), for example there could be a init space in which you load you application, a pre phase which precedes a particular event and then a post phase.\r\n\r\n###How to use\r\nTo use Eventspace.js you just have to download and include eventspace.js\r\nCreate your spaces of event:\r\n```\r\nES.add('init');\r\nES.add('pre');\r\nES.add('post');\r\n```\r\nOr just:\r\n```\r\nES.add(['init','pre','post']);\r\n```\r\nSet event for spaces:\r\n```\r\nES.on({\r\n    node: document.body,\r\n    event: 'click',\r\n    space: ['init', 'pre']\r\n}, function(){\r\n    alert('Clicked in space init or pre');\r\n})\r\n\r\nES.on({\r\n    node: document.body,\r\n    event: 'click',\r\n    space: ['post']\r\n}, function(){\r\n    alert('Clicked in space post');\r\n})\r\n```\r\nActivate spaces:\r\n```\r\nES.set('init');\r\n```\r\nAnd if you click on webpage body you will see an alert \"Clicked in space init or pre\"\r\n\r\nDeactivate spaces:\r\n```\r\nES.set();\r\n```\r\n\r\nAnd now if you click on webpage body you won't see any alert\r\n\r\n### Authors and Contributors\r\nPaolo Cifariello (@PaoloCifariello)","google":"","note":"Don't delete this file! It's used internally to help with page regeneration."}